Workbook

Sheet README
A1: Duvo AI – Prague office compliance self-audit (control mapping)
A2: Prepared 27 Oct 2026 (trial day). Purpose: one source of truth that drives (1) the findings report and (2) the remote self-audit app any office member can run.
A4: How to use
A5: 1. Controls tab: one row per control. Read 'Control', 'Why we check this' and 'Threat if missing', then follow 'How to check' and collect what 'What the proof looks like' describes.
A6: 2. Fill only the yellow columns: Status, Finding / notes, Risk, Owner, Effort, Last checked, Checked by. Everything else is the reference design.
A7: 3. Tier = how demanding the check is (see Tiers tab). Tiers are cumulative: to be ready at ☠☠ Medium you must also pass every ☠ Easy control.
A8: 4. 'Client visit' = Yes means the control is also in the quick pre-visit check (Client visit tab), to be run within 24 h before any client or auditor visit.
A9: 5. 'Automatable?' and 'Automation idea' show where the check or the control itself can run without a person (e.g., badge activates only when NDA + ID + approvals are complete).
A10: 6. Summary tab calculates readiness per tier, client-visit readiness and status by domain automatically.
A12: Example rows
A13: Fill the yellow columns with your own observations; leave the rest as the reference design.
A15: Important
... A17: NIS2 and DORA mappings reflect customer flow-down (Duvo supplies banks and critical entities), not confirmed direct applicability. See the Regulatory scope tab.

Sheet Summary
A1: Readiness summary (calculated)
A3: Tier (cumulative) | B3: Applicable controls | C3: Compliant | D3: Partial | E3: Non-compliant | F3: Not assessed | G3: Readiness %
A4: ☠ Easy ready | B4: =(COUNTIFS(Controls!$F$2:$F$74,"☠ Easy"))-(COUNTIFS(Controls!$F$2:$F$74,"☠ Easy",Controls!$R$2:$R$74,"N/A")) -> 27 | C4: =COUNTIFS(Controls!$F$2:$F$74,"☠ Easy",Controls!$R$2:$R$74,"Compliant") -> 0 | D4: =COUNTIFS(Controls!$F$2:$F$74,"☠ Easy",Controls!$R$2:$R$74,"Partial") -> 0 | E4: =COUNTIFS(Controls!$F$2:$F$74,"☠ Easy",Controls!$R$2:$R$74,"Non-compliant") -> 0 | F4: =COUNTIFS(Controls!$F$2:$F$74,"☠ Easy",Controls!$R$2:$R$74,"Not assessed") -> 27 | G4: =IFERROR(C4/B4,0) -> 0
A5: ☠☠ Medium ready | B5: =(COUNTIFS(Controls!$F$2:$F$74,"☠ Easy")+COUNTIFS(Controls!$F$2:$F$74,"☠☠ Medium"))-(COUNTIFS(Controls!$F$2:$F$74,"☠ Easy",Controls!$R$2:$R$74,"N/A")+COUNTIFS(Controls!$F$2:$F$74,"☠☠ Medium",Controls!$R$2:$R$74,"N/A")) -> 65 | C5: =COUNTIFS(Controls!$F$2:$F$74,"☠ Easy",Controls!$R$2:$R$74,"Compliant")+COUNTIFS(Controls!$F$2:$F$74,"☠☠ Medium",Controls!$R$2:$R$74,"Compliant") -> 0 | D5: =COUNTIFS(Controls!$F$2:$F$74,"☠ Easy",Controls!$R$2:$R$74,"Partial")+COUNTIFS(Controls!$F$2:$F$74,"☠☠ Medium",Controls!$R$2:$R$74,"Partial") -> 0 | E5: =COUNTIFS(Controls!$F$2:$F$74,"☠ Easy",Controls!$R$2:$R$74,"Non-compliant")+COUNTIFS(Controls!$F$2:$F$74,"☠☠ Medium",Controls!$R$2:$R$74,"Non-compliant") -> 0 | F5: =COUNTIFS(Controls!$F$2:$F$74,"☠ Easy",Controls!$R$2:$R$74,"Not assessed")+COUNTIFS(Controls!$F$2:$F$74,"☠☠ Medium",Controls!$R$2:$R$74,"Not assessed") -> 65 | G5: =IFERROR(C5/B5,0) -> 0
A6: ☠☠☠ Hard ready | B6: =(COUNTIFS(Controls!$F$2:$F$74,"☠ Easy")+COUNTIFS(Controls!$F$2:$F$74,"☠☠ Medium")+COUNTIFS(Controls!$F$2:$F$74,"☠☠☠ Hard"))-(COUNTIFS(Controls!$F$2:$F$74,"☠ Easy",Controls!$R$2:$R$74,"N/A")+COUNTIFS(Controls!$F$2:$F$74,"☠☠ Medium",Controls!$R$2:$R$74,"N/A")+COUNTIFS(Controls!$F$2:$F$74,"☠☠☠ Hard",Controls!$R$2:$R$74,"N/A")) -> 73 | C6: =COUNTIFS(Controls!$F$2:$F$74,"☠ Easy",Controls!$R$2:$R$74,"Compliant")+COUNTIFS(Controls!$F$2:$F$74,"☠☠ Medium",Controls!$R$2:$R$74,"Compliant")+COUNTIFS(Controls!$F$2:$F$74,"☠☠☠ Hard",Controls!$R$2:$R$74,"Compliant") -> 0 | D6: =COUNTIFS(Controls!$F$2:$F$74,"☠ Easy",Controls!$R$2:$R$74,"Partial")+COUNTIFS(Controls!$F$2:$F$74,"☠☠ Medium",Controls!$R$2:$R$74,"Partial")+COUNTIFS(Controls!$F$2:$F$74,"☠☠☠ Hard",Controls!$R$2:$R$74,"Partial") -> 0 | E6: =COUNTIFS(Controls!$F$2:$F$74,"☠ Easy",Controls!$R$2:$R$74,"Non-compliant")+COUNTIFS(Controls!$F$2:$F$74,"☠☠ Medium",Controls!$R$2:$R$74,"Non-compliant")+COUNTIFS(Controls!$F$2:$F$74,"☠☠☠ Hard",Controls!$R$2:$R$74,"Non-compliant") -> 0 | F6: =COUNTIFS(Controls!$F$2:$F$74,"☠ Easy",Controls!$R$2:$R$74,"Not assessed")+COUNTIFS(Controls!$F$2:$F$74,"☠☠ Medium",Controls!$R$2:$R$74,"Not assessed")+COUNTIFS(Controls!$F$2:$F$74,"☠☠☠ Hard",Controls!$R$2:$R$74,"Not assessed") -> 73 | G6: =IFERROR(C6/B6,0) -> 0
A7: Client-visit controls | B7: =COUNTIFS(Controls!$G$2:$G$74,"Yes")-COUNTIFS(Controls!$G$2:$G$74,"Yes",Controls!$R$2:$R$74,"N/A") -> 25 | C7: =COUNTIFS(Controls!$G$2:$G$74,"Yes",Controls!$R$2:$R$74,"Compliant") -> 0 | D7: =COUNTIFS(Controls!$G$2:$G$74,"Yes",Controls!$R$2:$R$74,"Partial") -> 0 | E7: =COUNTIFS(Controls!$G$2:$G$74,"Yes",Controls!$R$2:$R$74,"Non-compliant") -> 0 | F7: =COUNTIFS(Controls!$G$2:$G$74,"Yes",Controls!$R$2:$R$74,"Not assessed") -> 25 | G7: =IFERROR(C7/B7,0) -> 0
A9: Readiness % = Compliant ÷ applicable (N/A excluded). Partial counts as not ready.
A11: Domain | B11: Controls | C11: Compliant | D11: Partial | E11: Non-compliant | F11: Not assessed | G11: Open High risks
A12: Physical access & perimeter | B12: =COUNTIFS(Controls!$B$2:$B$74,$A12) -> 6 | C12: =COUNTIFS(Controls!$B$2:$B$74,$A12,Controls!$R$2:$R$74,"Compliant") -> 0 | D12: =COUNTIFS(Controls!$B$2:$B$74,$A12,Controls!$R$2:$R$74,"Partial") -> 0 | E12: =COUNTIFS(Controls!$B$2:$B$74,$A12,Controls!$R$2:$R$74,"Non-compliant") -> 0 | F12: =COUNTIFS(Controls!$B$2:$B$74,$A12,Controls!$R$2:$R$74,"Not assessed") -> 6 | G12: =COUNTIFS(Controls!$B$2:$B$74,$A12,Controls!$T$2:$T$74,"High",Controls!$R$2:$R$74,"<>Compliant",Controls!$R$2:$R$74,"<>N/A") -> 0
A13: Visitors | B13: =COUNTIFS(Controls!$B$2:$B$74,$A13) -> 8 | C13: =COUNTIFS(Controls!$B$2:$B$74,$A13,Controls!$R$2:$R$74,"Compliant") -> 0 | D13: =COUNTIFS(Controls!$B$2:$B$74,$A13,Controls!$R$2:$R$74,"Partial") -> 0 | E13: =COUNTIFS(Controls!$B$2:$B$74,$A13,Controls!$R$2:$R$74,"Non-compliant") -> 0 | F13: =COUNTIFS(Controls!$B$2:$B$74,$A13,Controls!$R$2:$R$74,"Not assessed") -> 8 | G13: =COUNTIFS(Controls!$B$2:$B$74,$A13,Controls!$T$2:$T$74,"High",Controls!$R$2:$R$74,"<>Compliant",Controls!$R$2:$R$74,"<>N/A") -> 0
A14: Badges & keys | B14: =COUNTIFS(Controls!$B$2:$B$74,$A14) -> 6 | C14: =COUNTIFS(Controls!$B$2:$B$74,$A14,Controls!$R$2:$R$74,"Compliant") -> 0 | D14: =COUNTIFS(Controls!$B$2:$B$74,$A14,Controls!$R$2:$R$74,"Partial") -> 0 | E14: =COUNTIFS(Controls!$B$2:$B$74,$A14,Controls!$R$2:$R$74,"Non-compliant") -> 0 | F14: =COUNTIFS(Controls!$B$2:$B$74,$A14,Controls!$R$2:$R$74,"Not assessed") -> 6 | G14: =COUNTIFS(Controls!$B$2:$B$74,$A14,Controls!$T$2:$T$74,"High",Controls!$R$2:$R$74,"<>Compliant",Controls!$R$2:$R$74,"<>N/A") -> 0
A15: CCTV & monitoring | B15: =COUNTIFS(Controls!$B$2:$B$74,$A15) -> 6 | C15: =COUNTIFS(Controls!$B$2:$B$74,$A15,Controls!$R$2:$R$74,"Compliant") -> 0 | D15: =COUNTIFS(Controls!$B$2:$B$74,$A15,Controls!$R$2:$R$74,"Partial") -> 0 | E15: =COUNTIFS(Controls!$B$2:$B$74,$A15,Controls!$R$2:$R$74,"Non-compliant") -> 0 | F15: =COUNTIFS(Controls!$B$2:$B$74,$A15,Controls!$R$2:$R$74,"Not assessed") -> 6 | G15: =COUNTIFS(Controls!$B$2:$B$74,$A15,Controls!$T$2:$T$74,"High",Controls!$R$2:$R$74,"<>Compliant",Controls!$R$2:$R$74,"<>N/A") -> 0
A16: Clean desk, screens & meeting rooms | B16: =COUNTIFS(Controls!$B$2:$B$74,$A16) -> 7 | C16: =COUNTIFS(Controls!$B$2:$B$74,$A16,Controls!$R$2:$R$74,"Compliant") -> 0 | D16: =COUNTIFS(Controls!$B$2:$B$74,$A16,Controls!$R$2:$R$74,"Partial") -> 0 | E16: =COUNTIFS(Controls!$B$2:$B$74,$A16,Controls!$R$2:$R$74,"Non-compliant") -> 0 | F16: =COUNTIFS(Controls!$B$2:$B$74,$A16,Controls!$R$2:$R$74,"Not assessed") -> 7 | G16: =COUNTIFS(Controls!$B$2:$B$74,$A16,Controls!$T$2:$T$74,"High",Controls!$R$2:$R$74,"<>Compliant",Controls!$R$2:$R$74,"<>N/A") -> 0
A17: Network & Wi-Fi | B17: =COUNTIFS(Controls!$B$2:$B$74,$A17) -> 5 | C17: =COUNTIFS(Controls!$B$2:$B$74,$A17,Controls!$R$2:$R$74,"Compliant") -> 0 | D17: =COUNTIFS(Controls!$B$2:$B$74,$A17,Controls!$R$2:$R$74,"Partial") -> 0 | E17: =COUNTIFS(Controls!$B$2:$B$74,$A17,Controls!$R$2:$R$74,"Non-compliant") -> 0 | F17: =COUNTIFS(Controls!$B$2:$B$74,$A17,Controls!$R$2:$R$74,"Not assessed") -> 5 | G17: =COUNTIFS(Controls!$B$2:$B$74,$A17,Controls!$T$2:$T$74,"High",Controls!$R$2:$R$74,"<>Compliant",Controls!$R$2:$R$74,"<>N/A") -> 0
A18: Devices & equipment | B18: =COUNTIFS(Controls!$B$2:$B$74,$A18) -> 4 | C18: =COUNTIFS(Controls!$B$2:$B$74,$A18,Controls!$R$2:$R$74,"Compliant") -> 0 | D18: =COUNTIFS(Controls!$B$2:$B$74,$A18,Controls!$R$2:$R$74,"Partial") -> 0 | E18: =COUNTIFS(Controls!$B$2:$B$74,$A18,Controls!$R$2:$R$74,"Non-compliant") -> 0 | F18: =COUNTIFS(Controls!$B$2:$B$74,$A18,Controls!$R$2:$R$74,"Not assessed") -> 4 | G18: =COUNTIFS(Controls!$B$2:$B$74,$A18,Controls!$T$2:$T$74,"High",Controls!$R$2:$R$74,"<>Compliant",Controls!$R$2:$R$74,"<>N/A") -> 0
A19: Media & disposal | B19: =COUNTIFS(Controls!$B$2:$B$74,$A19) -> 2 | C19: =COUNTIFS(Controls!$B$2:$B$74,$A19,Controls!$R$2:$R$74,"Compliant") -> 0 | D19: =COUNTIFS(Controls!$B$2:$B$74,$A19,Controls!$R$2:$R$74,"Partial") -> 0 | E19: =COUNTIFS(Controls!$B$2:$B$74,$A19,Controls!$R$2:$R$74,"Non-compliant") -> 0 | F19: =COUNTIFS(Controls!$B$2:$B$74,$A19,Controls!$R$2:$R$74,"Not assessed") -> 2 | G19: =COUNTIFS(Controls!$B$2:$B$74,$A19,Controls!$T$2:$T$74,"High",Controls!$R$2:$R$74,"<>Compliant",Controls!$R$2:$R$74,"<>N/A") -> 0
A20: Health & safety (BOZP) | B20: =COUNTIFS(Controls!$B$2:$B$74,$A20) -> 7 | C20: =COUNTIFS(Controls!$B$2:$B$74,$A20,Controls!$R$2:$R$74,"Compliant") -> 0 | D20: =COUNTIFS(Controls!$B$2:$B$74,$A20,Controls!$R$2:$R$74,"Partial") -> 0 | E20: =COUNTIFS(Controls!$B$2:$B$74,$A20,Controls!$R$2:$R$74,"Non-compliant") -> 0 | F20: =COUNTIFS(Controls!$B$2:$B$74,$A20,Controls!$R$2:$R$74,"Not assessed") -> 7 | G20: =COUNTIFS(Controls!$B$2:$B$74,$A20,Controls!$T$2:$T$74,"High",Controls!$R$2:$R$74,"<>Compliant",Controls!$R$2:$R$74,"<>N/A") -> 0
A21: Fire & emergency | B21: =COUNTIFS(Controls!$B$2:$B$74,$A21) -> 5 | C21: =COUNTIFS(Controls!$B$2:$B$74,$A21,Controls!$R$2:$R$74,"Compliant") -> 0 | D21: =COUNTIFS(Controls!$B$2:$B$74,$A21,Controls!$R$2:$R$74,"Partial") -> 0 | E21: =COUNTIFS(Controls!$B$2:$B$74,$A21,Controls!$R$2:$R$74,"Non-compliant") -> 0 | F21: =COUNTIFS(Controls!$B$2:$B$74,$A21,Controls!$R$2:$R$74,"Not assessed") -> 5 | G21: =COUNTIFS(Controls!$B$2:$B$74,$A21,Controls!$T$2:$T$74,"High",Controls!$R$2:$R$74,"<>Compliant",Controls!$R$2:$R$74,"<>N/A") -> 0
A22: People & legal obligations | B22: =COUNTIFS(Controls!$B$2:$B$74,$A22) -> 7 | C22: =COUNTIFS(Controls!$B$2:$B$74,$A22,Controls!$R$2:$R$74,"Compliant") -> 0 | D22: =COUNTIFS(Controls!$B$2:$B$74,$A22,Controls!$R$2:$R$74,"Partial") -> 0 | E22: =COUNTIFS(Controls!$B$2:$B$74,$A22,Controls!$R$2:$R$74,"Non-compliant") -> 0 | F22: =COUNTIFS(Controls!$B$2:$B$74,$A22,Controls!$R$2:$R$74,"Not assessed") -> 7 | G22: =COUNTIFS(Controls!$B$2:$B$74,$A22,Controls!$T$2:$T$74,"High",Controls!$R$2:$R$74,"<>Compliant",Controls!$R$2:$R$74,"<>N/A") -> 0
A23: Tenancy & shared building | B23: =COUNTIFS(Controls!$B$2:$B$74,$A23) -> 3 | C23: =COUNTIFS(Controls!$B$2:$B$74,$A23,Controls!$R$2:$R$74,"Compliant") -> 0 | D23: =COUNTIFS(Controls!$B$2:$B$74,$A23,Controls!$R$2:$R$74,"Partial") -> 0 | E23: =COUNTIFS(Controls!$B$2:$B$74,$A23,Controls!$R$2:$R$74,"Non-compliant") -> 0 | F23: =COUNTIFS(Controls!$B$2:$B$74,$A23,Controls!$R$2:$R$74,"Not assessed") -> 3 | G23: =COUNTIFS(Controls!$B$2:$B$74,$A23,Controls!$T$2:$T$74,"High",Controls!$R$2:$R$74,"<>Compliant",Controls!$R$2:$R$74,"<>N/A") -> 0
... A25: Incidents & continuity | B25: =COUNTIFS(Controls!$B$2:$B$74,$A25) -> 2 | C25: =COUNTIFS(Controls!$B$2:$B$74,$A25,Controls!$R$2:$R$74,"Compliant") -> 0 | D25: =COUNTIFS(Controls!$B$2:$B$74,$A25,Controls!$R$2:$R$74,"Partial") -> 0 | E25: =COUNTIFS(Controls!$B$2:$B$74,$A25,Controls!$R$2:$R$74,"Non-compliant") -> 0 | F25: =COUNTIFS(Controls!$B$2:$B$74,$A25,Controls!$R$2:$R$74,"Not assessed") -> 2 | G25: =COUNTIFS(Controls!$B$2:$B$74,$A25,Controls!$T$2:$T$74,"High",Controls!$R$2:$R$74,"<>Compliant",Controls!$R$2:$R$74,"<>N/A") -> 0
A26: Total | B26: =SUM(B12:B25) -> 73 | C26: =SUM(C12:C25) -> 0 | D26: =SUM(D12:D25) -> 0 | E26: =SUM(E12:E25) -> 0 | F26: =SUM(F12:F25) -> 73 | G26: =SUM(G12:G25) -> 0
A28: Automation potential
A29: Full | B29: =COUNTIFS(Controls!$P$2:$P$74,"Full") -> 23
A30: Partial | B30: =COUNTIFS(Controls!$P$2:$P$74,"Partial") -> 22
A31: No | B31: =COUNTIFS(Controls!$P$2:$P$74,"No") -> 28

Sheet Tiers
A1: Tier | B1: What it means | C1: Who would hold us to it | D1: Reference yardstick
A2: ☠ Easy | B2: Legal baseline and basic security hygiene. Failing here is a legal or obvious security problem. | C2: Czech authorities (labour/fire inspection, ÚOOÚ), insurers, any auditor. | D2: GDPR, Czech labour, H&S and fire law; ISO 27001 must-haves.
A3: ☠☠ Medium | B3: Certification-ready. What an ISO 27001 or SOC 2 auditor expects to see evidenced and operating. | C3: ISO 27001 certification body; SOC 2 auditor; most enterprise customers. | D3: ISO 27001:2022 Annex A; SOC 2 Trust Services Criteria.
A4: ☠☠☠ Hard | B4: Regulated-customer grade. What a bank or critical-entity customer will demand when auditing a supplier on site. | C4: Bank / critical-entity customers via NIS2 supply-chain and DORA contractual (audit/access) rights. | D4: NIS2 Art 21 + CZ Act 264/2025; DORA Art 28–30 flow-down; PCI DSS physical controls as yardstick.

Sheet Controls
A1: ID | B1: Domain | C1: Control (plain English) | D1: Why we check this | E1: Threat if missing | F1: Tier | G1: Client visit | H1: How to check (step by step) | I1: What the proof looks like | J1: GDPR / CZ privacy | K1: Czech law | L1: ISO 27001:2022 | M1: SOC 2 TSC | N1: NIS2 (Art. 21 / CZ 264/2025) | O1: AI Act / ISO 42001 | P1: Automatable? | Q1: Automation idea | R1: Status | S1: Finding / notes | T1: Risk | U1: Owner | V1: Effort (S/M/L) | W1: Last checked | X1: Checked by
A2: PA-01 | B2: Physical access & perimeter | C2: Every way into the office (main door, side doors, fire exits, goods lift) is locked and only opens with a badge or key. | D2: Only people we know and approved should be able to walk in. | E2: Walk-in theft of laptops; a stranger reading customer data on screens; someone plugging a device into our network. | F2: ☠ Easy | G2: Yes | H2: Walk every entrance. From the outside, try each door without a badge. Note any door that opens. | I2: Photo of each entrance and its reader/lock; list of entrances with result (opens / doesn't). | J2: Art 32 | K2: — | L2: A.7.1, A.7.2 | M2: CC6.4 | N2: Art 21(2)(i) | O2: — | P2: Partial | Q2: Door sensors on the access system alert in Slack if a door is forced open. | R2: Not assessed
A3: PA-02 | B3: Physical access & perimeter | C3: Doors are never propped open, and the system alerts if a door is held open too long. | D3: A propped door cancels every other access control. | E3: Tailgating: anyone walks in behind the cleaning crew or a delivery. | F3: ☠☠ Medium | G3: No | H3: At arrival time, watch the main door for 15 min. Ask the landlord/admin whether a door-held-open alarm exists and who receives it. | I3: Screenshot of the alarm setting or alert recipient; note of observation. | J3: Art 32 | K3: — | L3: A.7.2, A.7.4 | M3: CC6.4 | N3: Art 21(2)(i) | O3: — | P3: Full | Q3: Door-held-open > 60s → automatic alert to office owner channel. | R3: Not assessed
A4: PA-03 | B4: Physical access & perimeter | C4: Staff know to challenge or report anyone they don't recognise following them in. | D4: Social engineering beats locks. People are the last line. | E4: Fake courier / fake IT technician gains entry by following an employee. | F4: ☠☠ Medium | G4: Yes | H4: Ask 3 people in the office: 'What do you do if someone you don't know follows you through the door?' | I4: Training completion record covering tailgating; photo of 'no tailgating' sign; notes of the 3 answers. | J4: — | K4: — | L4: A.6.3, A.7.2 | M4: CC1.4, CC2.2 | N4: Art 21(2)(g) | O4: — | P4: Partial | Q4: LMS tracks completion; annual reminder sent automatically. | R4: Not assessed
A5: PA-04 | B5: Physical access & perimeter | C5: The network cabinet, server/comms room and any storage with equipment are separately locked; we know who holds the keys. | D5: Network equipment is the easiest way to get persistent access to everything. | E5: Rogue device on the switch; theft of equipment; tampering with Wi-Fi. | F5: ☠☠ Medium | G5: No | H5: Find the network cabinet/router. Is it locked? Who has the key? Is it ours or the landlord's? | I5: Photo of locked cabinet; key-holder list. | J5: Art 32 | K5: — | L5: A.7.3, A.7.6, A.7.12 | M5: CC6.4 | N5: Art 21(2)(i) | O5: — | P5: No | R5: Not assessed
A6: PA-05 | B6: Physical access & perimeter | C6: Door access logs are kept for a defined period and reviewed at least quarterly. | D6: Auditors and customers will ask 'who entered the office and when?'. We must be able to answer. | E6: Insider or ex-employee access goes unnoticed; we can't investigate an incident. | F6: ☠☠ Medium | G6: No | H6: Ask who runs the access system. Request a 7-day log export. Ask how long logs are kept and who reviews them. | I6: Log export sample; retention setting; dated review record. | J6: Art 5(1)(e), Art 30 | K6: Labour Code §316 (access logging is employee monitoring – proportionate, employees informed) | L6: A.7.2, A.8.15 | M6: CC6.4 | N6: Art 21(2)(i) | O6: — | P6: Full | Q6: Quarterly export auto-compared to HR roster; mismatches raised as a ticket (good Duvo agent use case). | R6: Not assessed
A7: PA-06 | B7: Physical access & perimeter | C7: Unusual access (nights, weekends, badge used by a leaver) triggers an alert. | D7: Regulated customers expect detective, not only preventive, controls. | E7: Break-in or misuse of a stolen badge discovered days later. | F7: ☠☠☠ Hard | G7: No | H7: Ask whether the access system can alert on out-of-hours use. Check if it's configured. | I7: Alert rule screenshot; one test alert. | J7: Art 32 | K7: — | L7: A.7.4, A.8.16 | M7: CC7.2 | N7: Art 21(2)(b) | O7: — | P7: Full | Q7: Rule: badge use 22:00–06:00 or weekends → alert to office owner + security. | R7: Not assessed
A8: VI-01 | B8: Visitors | C8: Every visitor's identity is checked against a photo ID on arrival (viewed, not copied). | D8: We need to know the person in the building is who they say they are. | E8: Impersonation ('I'm from the client / from IT'); a stranger with a visitor badge walking around. | F8: ☠☠ Medium | G8: Yes | H8: Arrive as / with a visitor. Is ID requested and actually looked at? | I8: Visitor procedure; check-in record showing 'ID verified: yes / by whom'. Do NOT store ID copies. | J8: Art 5(1)(c) – verify, don't copy | K8: Czech rules restrict copying ID cards – check visually only | L8: A.7.2 | M8: CC6.4 | N8: Art 21(2)(i) | O8: — | P8: Partial | Q8: Check-in tablet asks the host/receptionist to tick 'ID verified' before the badge prints. | R8: Not assessed
A9: VI-02 | B9: Visitors | C9: Every visitor is logged: name, company, host, time in, time out. | D9: In a fire we must know who is inside. In an incident we must know who was there. | E9: Missing person in an evacuation; no trail after a theft or data leak. | F9: ☠ Easy | G9: Yes | H9: Check whether there's a visitor book or digital log. Is today's visitor in it? | I9: Log entries for the last visits; retention period stated. | J9: Art 5(1)(e), Art 13, Art 30 | K9: — | L9: A.7.2 | M9: CC6.4 | N9: Art 21(2)(i) | O9: — | P9: Full | Q9: Host invites visitor via calendar → visitor gets pre-registration email → QR check-in creates the log entry automatically. | R9: Not assessed
A10: VI-03 | B10: Visitors | C10: Visitors are accompanied by their host at all times outside meeting rooms. | D10: Visitors shouldn't wander past screens and whiteboards. | E10: Shoulder-surfing of customer data; photos of our pipeline. | F10: ☠☠ Medium | G10: Yes | H10: Observe a visit. Was the visitor left alone in open areas? | I10: Visitor rules (1 page); observation note. | J10: Art 32 | K10: — | L10: A.7.2, A.7.6 | M10: CC6.4 | N10: Art 21(2)(i) | O10: — | P10: No | R10: Not assessed
A11: VI-04 | B11: Visitors | C11: Visitors wear a visibly different badge that stops working at the end of the day and is returned. | D11: Staff must be able to tell a visitor from a colleague at a glance. | E11: Visitor badges kept and reused to get back in. | F11: ☠☠ Medium | G11: Yes | H11: Look at a visitor badge. Does it look different? Does it expire? Count issued vs returned. | I11: Photo of visitor badge; badge config showing same-day expiry. | J11: — | K11: — | L11: A.7.2 | M11: CC6.4 | N11: Art 21(2)(i) | O11: — | P11: Full | Q11: Temporary QR badge auto-expires at 23:59 on the visit day. | R11: Not assessed
A12: VI-05 | B12: Visitors | C12: Visitors who will see more than a meeting room sign an NDA before they enter. | D12: We show customer workflows and automations on screens. That is confidential. | E12: Visitor discloses a customer's processes or our product roadmap. | F12: ☠☠ Medium | G12: Yes | H12: Ask the host: was an NDA signed? Where is it stored? | I12: Signed NDA linked to the visit record. | J12: — | K12: Civil Code (contractual confidentiality) | L12: A.6.6 | M12: C1.1, CC2.3 | N12: Art 21(2)(d) | O12: — | P12: Full | Q12: NDA e-signature link sent in the pre-registration email. No signature → no badge. | R12: Not assessed
A13: VI-06 | B13: Visitors | C13: Visitors receive a short privacy notice (visitor log, CCTV, Wi-Fi) before or at arrival. | D13: GDPR requires telling people what we collect about them, when we collect it. | E13: Complaint to the Czech DPA (ÚOOÚ); unhappy client legal team. | F13: ☠ Easy | G13: Yes | H13: Is there a notice at reception or in the invite email? | I13: Copy of the notice; screenshot of the invite email. | J13: Art 13, Act 110/2019 | K13: — | L13: A.5.34 | M13: P1.1 | N13: — | O13: — | P13: Full | Q13: Notice embedded in the pre-registration email; no manual step. | R13: Not assessed
A14: VI-07 | B14: Visitors | C14: Contractors, cleaners and maintenance follow the same process; they are supervised in sensitive areas and their access hours are limited. | D14: Cleaners and maintenance often have more access than staff, often out of hours. | E14: Classic social-engineering route; theft of devices at night. | F14: ☠☠ Medium | G14: No | H14: Ask who cleans, when, with what key/badge, and whether their contract includes confidentiality. | I14: Contractor list with access hours; contract confidentiality clause. | J14: Art 28 (if they handle personal data) | K14: — | L14: A.5.19, A.5.20, A.7.6 | M14: CC9.2 | N14: Art 21(2)(d) | O14: — | P14: Partial | Q14: Contractor badges scheduled to work only in agreed hours. | R14: Not assessed
A15: VI-08 | B15: Visitors | C15: Couriers and deliveries are handled at reception and don't enter the office. | D15: Couriers are the easiest disguise. | E15: Stranger in the office with a parcel as cover. | F15: ☠ Easy | G15: No | H15: Ask how deliveries arrive. Where do they stop? | I15: Delivery instruction (1 line) at reception / in building rules. | J15: — | K15: — | L15: A.7.2 | M15: CC6.4 | N15: — | O15: — | P15: No | R15: Not assessed
A16: BD-01 | B16: Badges & keys | C16: An office badge is issued only after identity is verified and the company confirms the person in writing (HR/manager approval). Fails at every tier if missing. | D16: Whoever holds a permanent badge has the same physical access as an employee. | E16: Anyone who claims to be a new joiner gets permanent access; no trail of who approved it. | F16: ☠ Easy | G16: No | H16: Ask how a new person gets a badge. Who approves? Is ID checked? Where is the record? | I16: Badge request with approver + date; HR record matching the badge holder. | J16: Art 32 | K16: — | L16: A.5.16, A.5.18, A.7.2 | M16: CC6.2, CC6.4 | N16: Art 21(2)(i) | O16: — | P16: Full | Q16: Badge activates only when HR system shows: signed contract + NDA + policy acknowledgement + security training complete + ID verified. | R16: Not assessed
A17: BD-02 | B17: Badges & keys | C17: Leavers' badges and keys are deactivated/returned on their last day. | D17: Ex-employees should not be able to walk back in. | E17: Disgruntled ex-employee access; badge sold or lost. | F17: ☠ Easy | G17: No | H17: Take the last 3 leavers. Are their badges inactive? Were keys returned? | I17: Offboarding checklist with badge deactivation date = last day. | J17: Art 32 | K17: — | L17: A.5.18, A.6.5 | M17: CC6.3, CC6.4 | N17: Art 21(2)(i) | O17: — | P17: Full | Q17: HR offboarding event deactivates the badge automatically at end of last day. | R17: Not assessed
A18: BD-03 | B18: Badges & keys | C18: The list of active badges is reconciled against current staff every quarter. | D18: Badges drift: contractors, interns, lost cards. | E18: Unknown active badges in circulation. | F18: ☠☠ Medium | G18: No | H18: Export active badges; compare with HR headcount for Prague. | I18: Dated reconciliation with differences explained. | J18: Art 5(1)(d) | K18: — | L18: A.5.18 | M18: CC6.2, CC6.4 | N18: Art 21(2)(i) | O18: — | P18: Full | Q18: Scheduled job compares badge list vs HR system and opens a ticket for every mismatch. | R18: Not assessed
A19: BD-04 | B19: Badges & keys | C19: Physical keys (doors, cabinets, lockers) are inventoried with named holders. | D19: Keys can't be revoked. We must know where every one is. | E19: Unrecorded key copies; no way to know who can open the cabinet. | F19: ☠☠ Medium | G19: No | H19: List all keys and who holds them. Ask the landlord about master keys. | I19: Key register. | J19: — | K19: — | L19: A.7.2, A.7.3 | M19: CC6.4 | N19: Art 21(2)(i) | O19: — | P19: No | R19: Not assessed
A20: BD-05 | B20: Badges & keys | C20: There is a simple lost-badge rule: report immediately, badge is blocked the same day. | D20: A lost badge is an open door until it's blocked. | E20: Found badge used to enter. | F20: ☠☠ Medium | G20: No | H20: Ask 2 staff: what would you do if you lost your badge? | I20: Rule published; example block record. | J20: — | K20: — | L20: A.6.8, A.7.2 | M20: CC6.4, CC7.3 | N20: Art 21(2)(b) | O20: — | P20: Partial | Q20: Slack shortcut /lostbadge blocks the badge and notifies the office owner. | R20: Not assessed
A21: BD-06 | B21: Badges & keys | C21: Badge access levels follow least privilege (e.g., only named people open the network cabinet / storage). | D21: Not everyone needs every door. | E21: Insider or stolen badge opens sensitive areas. | F21: ☠☠☠ Hard | G21: No | H21: Review access groups in the badge system. | I21: Access-group list with justification per group. | J21: Art 32 | K21: — | L21: A.5.15, A.5.18 | M21: CC6.4 | N21: Art 21(2)(i) | O21: — | P21: Partial | R21: Not assessed
A22: CV-01 | B22: CCTV & monitoring | C22: We know whether CCTV exists, who operates it (Duvo or landlord), and our role (controller / processor / neither) is written down. | D22: If cameras film our people or visitors, someone is legally responsible. It must be clear who. | E22: DPA fine; inability to get footage after an incident. | F22: ☠ Easy | G22: No | H22: Look for cameras inside the office and at entrances. Ask the landlord who runs them. | I22: Camera map; landlord confirmation; role statement. | J22: Art 24, 26, 28 | K22: ÚOOÚ CCTV guidance | L22: A.5.31, A.5.34 | M22: CC9.2, P criteria | N22: — | O22: — | P22: No | R22: Not assessed
A23: CV-02 | B23: CCTV & monitoring | C23: CCTV signs are posted before people enter the filmed area, with a link/QR to the full notice. | D23: People must be told before they are filmed. | E23: DPA complaint; reputational hit with a client visiting. | F23: ☠ Easy | G23: Yes | H23: Check every entrance for a sign. | I23: Photo of each sign; full notice text. | J23: Art 13 | K23: ÚOOÚ CCTV guidance | L23: A.5.34 | M23: P1.1 | N23: — | O23: — | P23: Full | Q23: Pre-visit email includes the CCTV notice; sign has QR to the live notice. | R23: Not assessed
A24: CV-03 | B24: CCTV & monitoring | C24: Cameras don't film desks, screens, kitchens, toilets or rest areas; employee monitoring is limited to what is necessary. | D24: Czech law strictly limits monitoring employees at work. Cameras on screens also leak data. | E24: Unlawful employee surveillance; cameras recording customer data on monitors. | F24: ☠ Easy | G24: No | H24: Check each camera's angle (ask for a still from each). | I24: Still image per camera; justification per camera. | J24: Art 5(1)(c), Art 6(1)(f) | K24: Labour Code §316 | L24: A.5.34, A.7.4 | M24: P criteria | N24: — | O24: — | P24: No | R24: Not assessed
A25: CV-04 | B25: CCTV & monitoring | C25: Footage is deleted automatically after a short, defined period. | D25: Keeping footage 'just in case' breaks GDPR. | E25: Over-retention fine; larger breach if the recorder is hacked. | F25: ☠ Easy | G25: No | H25: Ask the operator for the retention setting. | I25: Screenshot of retention setting. | J25: Art 5(1)(e) | K25: ÚOOÚ CCTV guidance | L25: A.5.34, A.8.10 | M25: P4.2 | N25: — | O25: — | P25: Full | Q25: Retention enforced by the recorder; set once, verify quarterly. | R25: Not assessed
A26: CV-05 | B26: CCTV & monitoring | C26: A legitimate-interest assessment (and DPIA if needed) and a record of processing exist for CCTV, access logs and the visitor log. | D26: These are the documents a DPA or a client's DPO will ask for first. | E26: Unable to justify the processing → order to stop + fine. | F26: ☠☠ Medium | G26: No | H26: Check the ROPA for entries on CCTV, access logs, visitor log. | I26: ROPA entries; LIA document. | J26: Art 6(1)(f), 30, 35 | K26: Act 110/2019 | L26: A.5.34 | M26: P criteria | N26: — | O26: — | P26: No | R26: Not assessed
A27: CV-06 | B27: CCTV & monitoring | C27: Only named people can view or export footage, and access is logged. | D27: Footage is personal data and can be misused. | E27: Footage leaked or used to track colleagues. | F27: ☠☠ Medium | G27: No | H27: Ask who can view footage and how. | I27: Access list; viewing log. | J27: Art 32 | K27: Labour Code §316 | L27: A.5.15, A.8.15 | M27: CC6.1 | N27: — | O27: — | P27: Partial | R27: Not assessed
A28: CD-01 | B28: Clean desk, screens & meeting rooms | C28: Clean desk: no customer documents, passwords, post-its or notebooks with customer data left on desks. | D28: Visitors, cleaners and other tenants see whatever we leave out. | E28: Customer data photographed; passwords on post-its. | F28: ☠☠ Medium | G28: Yes | H28: Walk the office at end of day. Photograph anything sensitive left out (blur it). | I28: Dated walk-through photos; clear-desk rule. | J28: Art 32 | K28: — | L28: A.7.7 | M28: C1.1 | N28: Art 21(2)(g) | O28: — | P28: No | R28: Not assessed
A29: CD-02 | B29: Clean desk, screens & meeting rooms | C29: Laptops lock automatically after a short idle time; enforced centrally. | D29: Unlocked laptops are open doors into customer systems. | E29: Anyone at an unattended laptop acts as us inside a customer's ERP. | F29: ☠☠ Medium | G29: Yes | H29: Ask IT for the MDM policy. Test: leave a laptop idle. | I29: MDM policy screenshot showing lock timeout. | J29: Art 32 | K29: — | L29: A.7.7, A.8.1 | M29: CC6.1 | N29: Art 21(2)(g) | O29: — | P29: Full | Q29: Enforced by MDM; compliance report pulled automatically. | R29: Not assessed
A30: CD-03 | B30: Clean desk, screens & meeting rooms | C30: Screens showing customer screen recordings or customer systems can't be seen from windows, corridors or shared areas; privacy filters where needed. | D30: Our product works with recordings of how customer employees do their jobs. That is their personal data and their business secrets. | E30: Customer data visible from the corridor or to another tenant. | F30: ☠☠☠ Hard | G30: Yes | H30: Stand at windows, doors and shared areas. Can you read any screen? | I30: Photos from viewpoints; seating plan noting privacy filters. | J30: Art 32 | K30: — | L30: A.7.7, A.7.8 | M30: C1.1 | N30: Art 21(2)(g) | O30: — | P30: No | R30: Not assessed
A31: CD-04 | B31: Clean desk, screens & meeting rooms | C31: Whiteboards and meeting rooms are cleared after use. No customer names, pipeline or architecture left on walls. | D31: A visiting client must never see another client's name or data. | E31: Confidentiality breach in front of a client; lost deal. | F31: ☠☠ Medium | G31: Yes | H31: Check every meeting room and whiteboard. | I31: Photos of cleared rooms. | J31: — | K31: — | L31: A.7.7 | M31: C1.1 | N31: Art 21(2)(g) | O31: — | P31: Partial | Q31: Calendar automation sends 'wipe the board' reminder at meeting end. | R31: Not assessed
A32: CD-05 | B32: Clean desk, screens & meeting rooms | C32: Meeting-room recording and AI note-takers are announced to attendees, and room devices aren't left recording. | D32: People have the right to know they are being recorded. Clients will ask. | E32: Recording a client without notice; recordings stored in unknown tools. | F32: ☠☠ Medium | G32: Yes | H32: Check room devices; ask which note-taker tools are used. | I32: Recording rule; tool list; example meeting notice. | J32: Art 6, Art 13 | K32: — | L32: A.5.34 | M32: P1.1 | N32: — | O32: AI Act Art 4 (staff literacy); ISO 42001 A.8 | P32: Partial | Q32: Calendar invite template includes the recording notice automatically. | R32: Not assessed
A33: CD-06 | B33: Clean desk, screens & meeting rooms | C33: Calls about customer matters happen in closed rooms or booths, not in open or shared areas. | D33: Our people and agents talk to suppliers, stores and customers by phone. | E33: Overheard customer details by another tenant or visitor. | F33: ☠☠ Medium | G33: No | H33: Observe for an hour. Are there booths? Are they used? | I33: Photo of booths; rule in onboarding. | J33: Art 32 | K33: — | L33: A.7.6 | M33: C1.1 | N33: — | O33: — | P33: No | R33: Not assessed
A34: CD-07 | B34: Clean desk, screens & meeting rooms | C34: Clean desk & clear screen walk-around: unattended desks have no unlocked screens, open laptops, documents, post-its or badges left behind. | D34: Policies and MDM settings only count if people actually follow them. This is the check that proves it. | E34: An unattended unlocked laptop gives anyone passing by our access to customer systems; documents and badges left out can be taken or photographed. | F34: ☠☠ Medium | G34: Yes | H34: Twice a day (e.g., at lunch and after 18:00), walk every desk. For each unattended desk note: screen unlocked? laptop left open/unsecured? paper, post-its, notebooks, badge left out? Do not touch anything; photograph and blur. | I34: Dated walk-around sheet: number of desks checked, number with issues, blurred photos. Trend over time. | J34: Art 32 | K34: — | L34: A.7.7, A.8.1 | M34: C1.1, CC6.1 | N34: Art 21(2)(g) | O34: — | P34: Partial | Q34: MDM shows how many devices are below the lock-timeout policy; the human walk-around covers paper and behaviour. A friendly Slack nudge goes to desk owners with findings. | R34: Not assessed
A35: NW-01 | B35: Network & Wi-Fi | C35: Guest Wi-Fi is separate from the staff/corporate network. | D35: Visitors' devices must not reach our devices. | E35: Visitor's infected laptop scans and attacks our machines. | F35: ☠☠ Medium | G35: Yes | H35: Join guest Wi-Fi. Can you see staff devices or the printer? | I35: Network diagram; screenshot of VLAN/SSID config; test note. | J35: Art 32 | K35: — | L35: A.8.20, A.8.22 | M35: CC6.6 | N35: Art 21(2)(g) | O35: — | P35: No | R35: Not assessed
A36: NW-02 | B36: Network & Wi-Fi | C36: Wi-Fi uses strong encryption; the guest password rotates and is not written on the wall. | D36: A password on the wall belongs to everyone in the building. | E36: Other tenants and passers-by on our network. | F36: ☠☠ Medium | G36: Yes | H36: Look for written passwords. Check Wi-Fi security type. | I36: Router config screenshot; rotation evidence. | J36: Art 32 | K36: — | L36: A.8.20 | M36: CC6.6 | N36: Art 21(2)(g), (h) | O36: — | P36: Full | Q36: Guest password auto-rotates weekly and is shown only on the check-in screen. | R36: Not assessed
A37: NW-03 | B37: Network & Wi-Fi | C37: Office network equipment has default passwords changed, current firmware, and a named owner (us or landlord). | D37: Default router passwords are publicly known. | E37: Network takeover from inside the building. | F37: ☠☠ Medium | G37: No | H37: Ask who manages the router/switch/APs. Check firmware date. | I37: Asset entry with owner; firmware version; admin account list. | J37: Art 32 | K37: — | L37: A.5.9, A.8.9, A.8.20 | M37: CC6.1, CC7.1 | N37: Art 21(2)(e), (g) | O37: — | P37: Partial | Q37: Firmware status monitored by the network vendor console. | R37: Not assessed
A38: NW-04 | B38: Network & Wi-Fi | C38: Live network ports in reception and meeting rooms are disabled or protected. | D38: A free port in a meeting room is a free entry point. | E38: Visitor plugs in a device and gets internal access. | F38: ☠☠☠ Hard | G38: No | H38: Find wall ports in public rooms. Plug in a laptop: do you get an address? | I38: Port list; switch config. | J38: Art 32 | K38: — | L38: A.8.20, A.7.12 | M38: CC6.6 | N38: Art 21(2)(g) | O38: — | P38: No | R38: Not assessed
A39: NW-05 | B39: Network & Wi-Fi | C39: Office network is treated as untrusted: staff reach company systems the same way as from home (SSO, MFA, VPN/ZTNA). | D39: We are remote-first. The office should be just another location, not a trusted zone. | E39: Compromise of the building network gives an attacker a shortcut into our systems. | F39: ☠☠ Medium | G39: No | H39: Ask IT whether any system is accessible only from the office IP. | I39: IT statement; list of IP allow-lists (should be none for the office). | J39: Art 32 | K39: — | L39: A.8.20, A.8.5 | M39: CC6.1, CC6.6 | N39: Art 21(2)(j) | O39: — | P39: No | R39: Not assessed
A40: DV-01 | B40: Devices & equipment | C40: All equipment in the office (laptops, monitors, docks, printers, TVs, IoT) is in the asset inventory with an owner. | D40: You can't protect what you don't know you have. | E40: Lost or stolen kit goes unnoticed. | F40: ☠☠ Medium | G40: No | H40: Count kit on site; compare with inventory. | I40: Inventory extract for Prague. | J40: — | K40: — | L40: A.5.9 | M40: CC6.1 | N40: Art 21(2)(i) | O40: — | P40: Partial | Q40: MDM auto-populates laptops; non-MDM kit added at delivery. | R40: Not assessed
A41: DV-02 | B41: Devices & equipment | C41: Printers use secure release (print only when you badge in), admin password changed, and scan-to-email locked down. | D41: Printouts left on a tray are the most common office leak. | E41: Customer documents left in the printer tray for anyone to take. | F41: ☠☠ Medium | G41: Yes | H41: Print something. Does it wait for you? Check the tray for left prints. | I41: Printer config screenshot; photo of empty tray. | J41: Art 32 | K41: — | L41: A.7.7, A.8.9 | M41: CC6.1 | N41: Art 21(2)(g) | O41: — | P41: Partial | R41: Not assessed
A42: DV-03 | B42: Devices & equipment | C42: Smart devices (TVs, conference systems, speakers, smart locks) are on an isolated network with accounts owned by Duvo. | D42: IoT devices are rarely patched and often have default passwords. | E42: Conference camera or TV used to spy on meetings or as a foothold. | F42: ☠☠☠ Hard | G42: No | H42: List smart devices; check network and account owner. | I42: Device list with network segment and owner. | J42: Art 32 | K42: — | L42: A.8.20, A.8.22 | M42: CC6.6 | N42: Art 21(2)(e) | O42: — | P42: No | R42: Not assessed
A43: DV-04 | B43: Devices & equipment | C43: Spare and loaner laptops are encrypted, enrolled in MDM and stored locked. | D43: Spare laptops are often forgotten and unencrypted. | E43: Theft of a spare laptop with old data on it. | F43: ☠☠ Medium | G43: No | H43: Find spare kit; check storage and MDM status. | I43: MDM compliance report; photo of locked storage. | J43: Art 32 | K43: — | L43: A.7.9, A.7.10, A.8.1 | M43: CC6.1, CC6.7 | N43: Art 21(2)(h) | O43: — | P43: Full | Q43: MDM reports encryption status automatically. | R43: Not assessed
A44: DS-01 | B44: Media & disposal | C44: Locked confidential-waste bins or a shredder are available, and they are used. | D44: Paper in the normal bin is public. | E44: Customer documents recovered from rubbish. | F44: ☠☠ Medium | G44: Yes | H44: Look for bins. Check the paper recycling for sensitive paper. | I44: Photo of bin; shredding vendor certificate. | J44: Art 32 | K44: — | L44: A.7.14 | M44: CC6.5, C1.2 | N44: — | O44: — | P44: No | R44: Not assessed
A45: DS-02 | B45: Media & disposal | C45: Old laptops, drives and phones are wiped or destroyed with a certificate, and handed to an authorised e-waste take-back. | D45: Deleted ≠ gone. | E45: Customer data recovered from a disposed laptop. | F45: ☠☠ Medium | G45: No | H45: Ask what happened to the last disposed device. | I45: Certificate of data destruction; e-waste handover record. | J45: Art 32 | K45: Act 542/2020 (end-of-life products / WEEE) | L45: A.7.14, A.8.10 | M45: CC6.5 | N45: Art 21(2)(i) | O45: — | P45: Partial | Q45: MDM remote wipe triggered when a device is marked 'to dispose'. | R45: Not assessed
A46: HS-01 | B46: Health & safety (BOZP) | C46: A written workplace risk assessment exists for the new Prague office. | D46: Mandatory for every employer in Czechia. It's the base document for everything else in safety. | E46: Labour inspectorate fine; liability if someone is injured. | F46: ☠ Easy | G46: No | H46: Ask HR/OZO for the risk assessment dated after the move. | I46: Signed risk assessment for this address. | J46: — | K46: Labour Code §102; Act 309/2006 | L46: A.7.5 (environmental threats) | M46: A1.2 | N46: — | O46: — | P46: No | R46: Not assessed
A47: HS-02 | B47: Health & safety (BOZP) | C47: Duvo has a competent H&S person (OZO, internal or external) appointed. | D47: Czech law requires a qualified person to support the employer on safety. | E47: No one competent to run safety; inspection fine. | F47: ☠ Easy | G47: No | H47: Ask who the OZO is; get the contract. | I47: OZO contract or appointment. | J47: — | K47: Act 309/2006 §9 | L47: A.5.2 | M47: CC1.3 | N47: — | O47: — | P47: No | R47: Not assessed
A48: HS-03 | B48: Health & safety (BOZP) | C48: Every employee working in the office has received H&S training, and it's recorded. | D48: Required at onboarding and when the workplace changes (like a new office). | E48: Injury + no training record = employer liability. | F48: ☠ Easy | G48: No | H48: Check training records for Prague staff since the move. | I48: Signed/recorded training list. | J48: — | K48: Labour Code §103 | L48: A.6.3 | M48: CC1.4 | N48: Art 21(2)(g) | O48: — | P48: Full | Q48: LMS module assigned automatically on 'works from Prague office' flag; badge gate (BD-01) checks it. | R48: Not assessed
A49: HS-04 | B49: Health & safety (BOZP) | C49: First-aid kit is stocked and visible; people know who to call. | D49: Basic duty of care. | E49: Delay in first aid. | F49: ☠ Easy | G49: No | H49: Find the kit; check contents and expiry dates. | I49: Photo of kit; contents checklist with date. | J49: — | K49: Labour Code §102 | L49: — | M49: — | N49: — | O49: — | P49: Partial | Q49: Calendar reminder every 6 months to check expiry dates. | R49: Not assessed
A50: HS-05 | B50: Health & safety (BOZP) | C50: There is an injury log book and people know to report injuries. | D50: Mandatory record, even for minor injuries. | E50: Unrecorded injury; fine; disputed claims. | F50: ☠ Easy | G50: No | H50: Ask where the injury book (kniha úrazů) is. | I50: Photo of the book or digital log. | J50: — | K50: Labour Code §105; Gov. Decree 201/2010 | L50: — | M50: — | N50: — | O50: — | P50: No | R50: Not assessed
A51: HS-06 | B51: Health & safety (BOZP) | C51: Lighting, temperature, ventilation and desk/screen ergonomics are adequate. | D51: Czech workplace hygiene rules set minimums for screen work. | E51: Health complaints; inspection findings. | F51: ☠ Easy | G51: No | H51: Walk the office; ask staff about temperature, glare, chairs. | I51: Short checklist; OZO note. | J51: — | K51: Gov. Decree 361/2007 | L51: — | M51: — | N51: — | O51: — | P51: No | R51: Not assessed
A52: HS-07 | B52: Health & safety (BOZP) | C52: Electrical installation and appliances (kettles, chargers, monitors, extension leads) have valid inspections (revize), with records. | D52: Often forgotten after a move; a common fire cause. | E52: Electrical fire; insurance refusal. | F52: ☠ Easy | G52: No | H52: Ask landlord for the fixed-installation inspection report; ask who inspects our appliances. | I52: Inspection reports with dates. | J52: — | K52: Act 309/2006 §4; ČSN 33 1500 / 33 1600 | L52: A.7.11, A.7.13 | M52: A1.2 | N52: Art 21(2)(c) | O52: — | P52: Partial | Q52: Inspection due dates in a shared calendar with automatic reminders. | R52: Not assessed
A53: FR-01 | B53: Fire & emergency | C53: Fire-protection documentation exists for our activity category, and responsibilities between Duvo and landlord are clear. | D53: Fire law applies to every company with premises. | E53: Fine; uninsured damage. | F53: ☠ Easy | G53: No | H53: Ask landlord and OZO for fire documentation and the split of duties. | I53: Fire documentation; landlord responsibility statement. | J53: — | K53: Act 133/1985; Decree 246/2001 | L53: A.7.5 | M53: A1.2 | N53: Art 21(2)(c) | O53: — | P53: No | R53: Not assessed
A54: FR-02 | B54: Fire & emergency | C54: Extinguishers are present, accessible and inspected at least yearly. | D54: Legal requirement; first defence. | E54: Unusable extinguisher in a fire. | F54: ☠ Easy | G54: No | H54: Check each extinguisher tag date. | I54: Photo of tags. | J54: — | K54: Decree 246/2001 | L54: A.7.5 | M54: A1.2 | N54: — | O54: — | P54: Partial | Q54: Inspection due date in the shared calendar. | R54: Not assessed
A55: FR-03 | B55: Fire & emergency | C55: Escape routes are marked, never blocked, and emergency lighting works. | D55: People need to get out in the dark and in smoke. | E55: Blocked exit in an emergency. | F55: ☠ Easy | G55: Yes | H55: Walk escape routes. Anything stored in them? | I55: Photos of routes and signs. | J55: — | K55: Act 133/1985 | L55: A.7.5 | M55: A1.2 | N55: — | O55: — | P55: No | R55: Not assessed
A56: FR-04 | B56: Fire & emergency | C56: An evacuation plan and assembly point are posted, and visitors are told; the visitor log is used for headcount. | D56: Visitors don't know the building. | E56: Visitor left behind in an evacuation. | F56: ☠ Easy | G56: Yes | H56: Find the evacuation plan. Ask a visitor if they were told the assembly point. | I56: Photo of plan; visitor briefing line in the check-in flow. | J56: — | K56: Act 133/1985 | L56: A.7.5 | M56: A1.2 | N56: Art 21(2)(c) | O56: — | P56: Full | Q56: Assembly point shown on the check-in screen; live visitor list exportable to phone for headcount. | R56: Not assessed
A57: FR-05 | B57: Fire & emergency | C57: Staff have received fire-safety training, and it's recorded. | D57: Legal requirement alongside H&S training. | E57: Panic and injury; fine. | F57: ☠ Easy | G57: No | H57: Check training records. | I57: Training record. | J57: — | K57: Act 133/1985 | L57: A.6.3 | M57: CC1.4 | N57: — | O57: — | P57: Full | Q57: Bundled into the H&S LMS module (HS-03). | R57: Not assessed
A58: PL-01 | B58: People & legal obligations | C58: If the Czech employer has 50+ employees, an internal whistleblowing channel and a designated person exist. | D58: Legal obligation above the threshold; also expected by enterprise customers. | E58: Fine; whistleblower goes external first. | F58: ☠ Easy | G58: No | H58: Confirm Czech entity headcount (average). If ≥50, check the channel. | I58: Headcount; channel description; designated person. | J58: Art 32 (reports contain personal data) | K58: Act 171/2023 (applies from 50 employees) | L58: A.5.31, A.6.8 | M58: CC2.3 | N58: — | O58: — | P58: Partial | Q58: Use a whistleblowing tool with anonymous intake and statutory deadline tracking. | R58: Not assessed
A59: PL-02 | B59: People & legal obligations | C59: If the Czech employer has 25+ employees, the disability employment quota is met (employment, purchase of products/services, or levy) and reported annually. | D59: Often missed by fast-growing startups. | E59: Levy and fine. | F59: ☠ Easy | G59: No | H59: Confirm average headcount; ask HR/payroll how the quota is handled. | I59: Annual quota report. | J59: — | K59: Act 435/2004 | L59: A.5.31 | M59: — | N59: — | O59: — | P59: No | R59: Not assessed
A60: PL-03 | B60: People & legal obligations | C60: Employees are told in writing what is monitored at the office (access logs, CCTV, Wi-Fi) and why. | D60: Czech labour law requires informing employees about monitoring. | E60: Unlawful monitoring; works council/union or inspection complaint. | F60: ☠ Easy | G60: No | H60: Check the employee notice / handbook. | I60: Employee privacy notice section; acknowledgement. | J60: Art 13 | K60: Labour Code §316 | L60: A.5.34 | M60: P1.1 | N60: — | O60: — | P60: Full | Q60: Notice included in onboarding acknowledgement (BD-01 gate). | R60: Not assessed
A61: PL-04 | B61: People & legal obligations | C61: Everyone with a badge has signed confidentiality terms and acknowledged the acceptable-use and security policies. | D61: Customers will ask for this evidence for every person who touches their data. | E61: No legal basis to act against a leak. | F61: ☠☠ Medium | G61: No | H61: Sample 5 badge holders; find their signed documents. | I61: Signed NDA/contract clause + policy acknowledgement per person. | J61: Art 28(3)(b), Art 32(4) | K61: Labour Code (confidentiality in contract) | L61: A.6.2, A.6.6, A.5.10 | M61: CC1.1, CC2.2 | N61: Art 21(2)(i) | O61: — | P61: Full | Q61: Part of the badge activation gate (BD-01). | R61: Not assessed
A62: PL-05 | B62: People & legal obligations | C62: Annual security awareness training covers physical security, social engineering and AI use; completion is tracked. | D62: NIS2 supply-chain clauses and customers ask for proof of training. AI literacy is a legal duty for AI providers. | E62: Staff fall for tailgating or pretexting; AI tools misused with customer data. | F62: ☠☠ Medium | G62: No | H62: Check LMS completion for Prague staff. | I62: Completion report; training content outline. | J62: Art 32(4), Art 39 | K62: — | L62: A.6.3 | M62: CC1.4, CC2.2 | N62: Art 21(2)(g), Art 20(2) | O62: AI Act Art 4; ISO 42001 A.4 | P62: Full | Q62: LMS assigns and chases automatically; report exported quarterly. | R62: Not assessed
A63: PL-06 | B63: People & legal obligations | C63: Office-related processing (visitor log, access logs, CCTV, Wi-Fi logs) is in the record of processing activities. | D63: First document a client DPO or the DPA asks for. | E63: Unable to show accountability. | F63: ☠☠ Medium | G63: No | H63: Check ROPA. | I63: ROPA entries. | J63: Art 30, Art 5(2) | K63: Act 110/2019 | L63: A.5.34 | M63: P criteria | N63: — | O63: — | P63: No | R63: Not assessed
A64: PL-07 | B64: People & legal obligations | C64: Pre-employment checks are done to the level allowed by Czech law and proportionate to the role. | D64: Bank and critical-entity customers often require screening for people accessing their data. | E64: Customer contract breach; insider risk. | F64: ☠☠☠ Hard | G64: No | H64: Ask HR what checks are done and for which roles. | I64: Screening policy; per-role matrix. | J64: Art 6, Art 10 | K64: Labour Code §316(4) (limits on what employer may ask) | L64: A.6.1 | M64: CC1.4 | N64: Art 21(2)(i) | O64: — | P64: Partial | R64: Not assessed
A65: TN-01 | B65: Tenancy & shared building | C65: A responsibility matrix with the landlord exists: access system, reception, CCTV, fire, cleaning, network, utilities. | D65: In a new office, everyone assumes someone else does it. | E65: Gaps nobody owns (e.g., CCTV retention, fire inspections). | F65: ☠☠ Medium | G65: No | H65: Go through the lease/building rules; fill the matrix with the facility manager. | I65: Signed or agreed matrix. | J65: Art 26 / 28 (if landlord processes our people's data) | K65: — | L65: A.5.19, A.5.20, A.7.1 | M65: CC9.2 | N65: Art 21(2)(d) | O65: — | P65: No | R65: Not assessed
A66: TN-02 | B66: Tenancy & shared building | C66: Shared spaces (reception, kitchen, shared meeting rooms) are treated as public: no confidential material or conversations. | D66: Other tenants are strangers. | E66: Competitor or another tenant overhears or sees customer details. | F66: ☠☠ Medium | G66: Yes | H66: Identify shared spaces. Check for left material. | I66: Floor plan marking shared areas; rule in onboarding. | J66: Art 32 | K66: — | L66: A.7.1, A.7.6 | M66: C1.1 | N66: — | O66: — | P66: No | R66: Not assessed
A67: TN-03 | B67: Tenancy & shared building | C67: Building services vendors (cleaning, maintenance, security guard) have confidentiality obligations and controlled keys. | D67: They are inside our office when we are not. | E67: Theft or snooping out of hours. | F67: ☠☠ Medium | G67: No | H67: Ask for the vendor contracts (via landlord if needed). | I67: Contract clause; key/badge list for vendors. | J67: Art 28 (if applicable) | K67: — | L67: A.5.19, A.5.20 | M67: CC9.2 | N67: Art 21(2)(d) | O67: — | P67: No | R67: Not assessed
A68: AR-01 | B68: Audit readiness & client visits | C68: A named Prague office security owner and a deputy exist. | D68: Remote-first means someone local must own the office. | E68: Nobody runs checks; issues aren't fixed. | F68: ☠ Easy | G68: No | H68: Confirm names. | I68: Named owner in the RACI / this sheet's Owner column. | J68: — | K68: — | L68: A.5.2 | M68: CC1.3 | N68: Art 20 / Art 21(2)(a) | O68: — | P68: No | R68: Not assessed
A69: AR-02 | B69: Audit readiness & client visits | C69: This self-audit runs quarterly and after any office change; results and fixes are tracked. | D69: Shows the control is operating over time, which SOC 2 Type II and customer audits test. | E69: Controls decay unnoticed between audits. | F69: ☠☠ Medium | G69: No | H69: Check the last completed run and open actions. | I69: Dated completed checklists; action tracker. | J69: Art 32(1)(d) | K69: — | L69: Clause 9.1, 9.2; A.5.35 | M69: CC4.1 | N69: Art 21(2)(f) | O69: — | P69: Full | Q69: Recurring task assigned to the office owner; app records results; overdue → escalation. | R69: Not assessed
A70: AR-03 | B70: Audit readiness & client visits | C70: A client-visit evidence pack is ready: certifications or roadmap, key policies, this office's latest audit results, contact for security questions. | D70: Bank and critical-entity customers (NIS2/DORA flow-down) may audit us on site at short notice. | E70: We look unprepared in front of a regulated customer. | F70: ☠☠☠ Hard | G70: Yes | H70: Check the pack exists and is current (< 3 months). | I70: Pack index with dates. | J70: — | K70: — | L70: A.5.31, A.5.36 | M70: CC2.3 | N70: Art 21(2)(d) | O70: — | P70: Partial | Q70: Pack auto-assembled from the document repository; freshness flagged. | R70: Not assessed
A71: AR-04 | B71: Audit readiness & client visits | C71: A quick pre-visit check (the 'Client visit' tab) is run within 24 h before every client or auditor visit. | D71: First impressions are evidence. | E71: Other clients' names on whiteboards; visitor not logged; open doors. | F71: ☠☠☠ Hard | G71: Yes | H71: Check the record for the last client visit. | I71: Completed 'Client visit' checklist dated before the visit. | J71: — | K71: — | L71: A.5.35 | M71: CC4.1 | N71: Art 21(2)(f) | O71: — | P71: Full | Q71: Calendar event with an external client domain → checklist automatically sent to the office owner 24 h before. | R71: Not assessed
A72: AR-05 | B72: Audit readiness & client visits | C72: A legal and regulatory register covering the office (Czech law + frameworks) is kept and reviewed yearly. | D72: Shows we know what applies to us; required by ISO. | E72: Missed legal obligations after growth (thresholds crossed). | F72: ☠☠ Medium | G72: No | H72: Check the 'Regulatory scope' tab is reviewed and dated. | I72: Dated register. | J72: Art 5(2) | K72: — | L72: A.5.31 | M72: CC3.1 | N72: Art 21(2)(a) | O72: — | P72: Partial | Q72: Headcount thresholds (25 / 50) monitored from HR system; alert when crossed. | R72: Not assessed
A73: IR-01 | B73: Incidents & continuity | C73: Everyone knows how to report a physical security event (stranger, break-in, lost laptop/badge) and it's posted in the office. | D73: Fast reporting limits damage and meets breach deadlines. | E73: Lost laptop reported days later; 72 h GDPR breach clock missed. | F73: ☠ Easy | G73: Yes | H73: Ask 2 people how they'd report a lost laptop. Look for the notice. | I73: Poster photo; incident procedure. | J73: Art 33, 34 | K73: — | L73: A.5.24, A.6.8 | M73: CC7.3, CC7.4 | N73: Art 21(2)(b), Art 23 | O73: — | P73: Partial | Q73: Single Slack shortcut / form routes to security and opens the incident record. | R73: Not assessed
A74: IR-02 | B74: Incidents & continuity | C74: If the office is unusable, everyone can work remotely with no loss of service, and this is documented. | D74: Our strength as remote-first, but it must be written down to count as evidence. | E74: Customer asks for continuity evidence and we have none. | F74: ☠☠ Medium | G74: No | H74: Check BCP mentions the office and the remote fallback. | I74: BCP section; last test date. | J74: Art 32(1)(b), (c) | K74: — | L74: A.5.29, A.5.30 | M74: A1.2, CC9.1 | N74: Art 21(2)(c) | O74: — | P74: No | R74: Not assessed

Sheet Client visit
A1: Client-visit quick check — run within 24 h before any client or auditor visit
A2: Visit date: | C2: Client: | E2: Checked by:
A4: ID | B4: Control (from Controls tab) | C4: How to check | D4: Tier | E4: Quick result | F4: Note | G4: Latest full-audit status
A5: PA-01 | B5: =INDEX(Controls!$C$2:$C$74,MATCH($A5,Controls!$A$2:$A$74,0)) -> Every way into the office (main door, side doors, fire exits, goods lift) is locked and only opens with a badge or key. | C5: =INDEX(Controls!$H$2:$H$74,MATCH($A5,Controls!$A$2:$A$74,0)) -> Walk every entrance. From the outside, try each door without a badge. Note any door that opens. | D5: =INDEX(Controls!$F$2:$F$74,MATCH($A5,Controls!$A$2:$A$74,0)) -> ☠ Easy | G5: =INDEX(Controls!$R$2:$R$74,MATCH($A5,Controls!$A$2:$A$74,0)) -> Not assessed
A6: PA-03 | B6: =INDEX(Controls!$C$2:$C$74,MATCH($A6,Controls!$A$2:$A$74,0)) -> Staff know to challenge or report anyone they don't recognise following them in. | C6: =INDEX(Controls!$H$2:$H$74,MATCH($A6,Controls!$A$2:$A$74,0)) -> Ask 3 people in the office: 'What do you do if someone you don't know follows you through the door?' | D6: =INDEX(Controls!$F$2:$F$74,MATCH($A6,Controls!$A$2:$A$74,0)) -> ☠☠ Medium | G6: =INDEX(Controls!$R$2:$R$74,MATCH($A6,Controls!$A$2:$A$74,0)) -> Not assessed
A7: VI-01 | B7: =INDEX(Controls!$C$2:$C$74,MATCH($A7,Controls!$A$2:$A$74,0)) -> Every visitor's identity is checked against a photo ID on arrival (viewed, not copied). | C7: =INDEX(Controls!$H$2:$H$74,MATCH($A7,Controls!$A$2:$A$74,0)) -> Arrive as / with a visitor. Is ID requested and actually looked at? | D7: =INDEX(Controls!$F$2:$F$74,MATCH($A7,Controls!$A$2:$A$74,0)) -> ☠☠ Medium | G7: =INDEX(Controls!$R$2:$R$74,MATCH($A7,Controls!$A$2:$A$74,0)) -> Not assessed
A8: VI-02 | B8: =INDEX(Controls!$C$2:$C$74,MATCH($A8,Controls!$A$2:$A$74,0)) -> Every visitor is logged: name, company, host, time in, time out. | C8: =INDEX(Controls!$H$2:$H$74,MATCH($A8,Controls!$A$2:$A$74,0)) -> Check whether there's a visitor book or digital log. Is today's visitor in it? | D8: =INDEX(Controls!$F$2:$F$74,MATCH($A8,Controls!$A$2:$A$74,0)) -> ☠ Easy | G8: =INDEX(Controls!$R$2:$R$74,MATCH($A8,Controls!$A$2:$A$74,0)) -> Not assessed
A9: VI-03 | B9: =INDEX(Controls!$C$2:$C$74,MATCH($A9,Controls!$A$2:$A$74,0)) -> Visitors are accompanied by their host at all times outside meeting rooms. | C9: =INDEX(Controls!$H$2:$H$74,MATCH($A9,Controls!$A$2:$A$74,0)) -> Observe a visit. Was the visitor left alone in open areas? | D9: =INDEX(Controls!$F$2:$F$74,MATCH($A9,Controls!$A$2:$A$74,0)) -> ☠☠ Medium | G9: =INDEX(Controls!$R$2:$R$74,MATCH($A9,Controls!$A$2:$A$74,0)) -> Not assessed
A10: VI-04 | B10: =INDEX(Controls!$C$2:$C$74,MATCH($A10,Controls!$A$2:$A$74,0)) -> Visitors wear a visibly different badge that stops working at the end of the day and is returned. | C10: =INDEX(Controls!$H$2:$H$74,MATCH($A10,Controls!$A$2:$A$74,0)) -> Look at a visitor badge. Does it look different? Does it expire? Count issued vs returned. | D10: =INDEX(Controls!$F$2:$F$74,MATCH($A10,Controls!$A$2:$A$74,0)) -> ☠☠ Medium | G10: =INDEX(Controls!$R$2:$R$74,MATCH($A10,Controls!$A$2:$A$74,0)) -> Not assessed
A11: VI-05 | B11: =INDEX(Controls!$C$2:$C$74,MATCH($A11,Controls!$A$2:$A$74,0)) -> Visitors who will see more than a meeting room sign an NDA before they enter. | C11: =INDEX(Controls!$H$2:$H$74,MATCH($A11,Controls!$A$2:$A$74,0)) -> Ask the host: was an NDA signed? Where is it stored? | D11: =INDEX(Controls!$F$2:$F$74,MATCH($A11,Controls!$A$2:$A$74,0)) -> ☠☠ Medium | G11: =INDEX(Controls!$R$2:$R$74,MATCH($A11,Controls!$A$2:$A$74,0)) -> Not assessed
A12: VI-06 | B12: =INDEX(Controls!$C$2:$C$74,MATCH($A12,Controls!$A$2:$A$74,0)) -> Visitors receive a short privacy notice (visitor log, CCTV, Wi-Fi) before or at arrival. | C12: =INDEX(Controls!$H$2:$H$74,MATCH($A12,Controls!$A$2:$A$74,0)) -> Is there a notice at reception or in the invite email? | D12: =INDEX(Controls!$F$2:$F$74,MATCH($A12,Controls!$A$2:$A$74,0)) -> ☠ Easy | G12: =INDEX(Controls!$R$2:$R$74,MATCH($A12,Controls!$A$2:$A$74,0)) -> Not assessed
A13: CV-02 | B13: =INDEX(Controls!$C$2:$C$74,MATCH($A13,Controls!$A$2:$A$74,0)) -> CCTV signs are posted before people enter the filmed area, with a link/QR to the full notice. | C13: =INDEX(Controls!$H$2:$H$74,MATCH($A13,Controls!$A$2:$A$74,0)) -> Check every entrance for a sign. | D13: =INDEX(Controls!$F$2:$F$74,MATCH($A13,Controls!$A$2:$A$74,0)) -> ☠ Easy | G13: =INDEX(Controls!$R$2:$R$74,MATCH($A13,Controls!$A$2:$A$74,0)) -> Not assessed
A14: CD-01 | B14: =INDEX(Controls!$C$2:$C$74,MATCH($A14,Controls!$A$2:$A$74,0)) -> Clean desk: no customer documents, passwords, post-its or notebooks with customer data left on desks. | C14: =INDEX(Controls!$H$2:$H$74,MATCH($A14,Controls!$A$2:$A$74,0)) -> Walk the office at end of day. Photograph anything sensitive left out (blur it). | D14: =INDEX(Controls!$F$2:$F$74,MATCH($A14,Controls!$A$2:$A$74,0)) -> ☠☠ Medium | G14: =INDEX(Controls!$R$2:$R$74,MATCH($A14,Controls!$A$2:$A$74,0)) -> Not assessed
A15: CD-02 | B15: =INDEX(Controls!$C$2:$C$74,MATCH($A15,Controls!$A$2:$A$74,0)) -> Laptops lock automatically after a short idle time; enforced centrally. | C15: =INDEX(Controls!$H$2:$H$74,MATCH($A15,Controls!$A$2:$A$74,0)) -> Ask IT for the MDM policy. Test: leave a laptop idle. | D15: =INDEX(Controls!$F$2:$F$74,MATCH($A15,Controls!$A$2:$A$74,0)) -> ☠☠ Medium | G15: =INDEX(Controls!$R$2:$R$74,MATCH($A15,Controls!$A$2:$A$74,0)) -> Not assessed
A16: CD-03 | B16: =INDEX(Controls!$C$2:$C$74,MATCH($A16,Controls!$A$2:$A$74,0)) -> Screens showing customer screen recordings or customer systems can't be seen from windows, corridors or shared areas; privacy filters where needed. | C16: =INDEX(Controls!$H$2:$H$74,MATCH($A16,Controls!$A$2:$A$74,0)) -> Stand at windows, doors and shared areas. Can you read any screen? | D16: =INDEX(Controls!$F$2:$F$74,MATCH($A16,Controls!$A$2:$A$74,0)) -> ☠☠☠ Hard | G16: =INDEX(Controls!$R$2:$R$74,MATCH($A16,Controls!$A$2:$A$74,0)) -> Not assessed
... A29: IR-01 | B29: =INDEX(Controls!$C$2:$C$74,MATCH($A29,Controls!$A$2:$A$74,0)) -> Everyone knows how to report a physical security event (stranger, break-in, lost laptop/badge) and it's posted in the office. | C29: =INDEX(Controls!$H$2:$H$74,MATCH($A29,Controls!$A$2:$A$74,0)) -> Ask 2 people how they'd report a lost laptop. Look for the notice. | D29: =INDEX(Controls!$F$2:$F$74,MATCH($A29,Controls!$A$2:$A$74,0)) -> ☠ Easy | G29: =INDEX(Controls!$R$2:$R$74,MATCH($A29,Controls!$A$2:$A$74,0)) -> Not assessed

Sheet Regulatory scope
A1: Framework / law | B1: Applies to Duvo? | C1: Why / how | D1: Office relevance | E1: Note
A2: GDPR (EU 2016/679) | B2: Yes – direct | C2: Duvo processes staff, visitor and customer-employee data (incl. screen recordings). | D2: Visitor log, access logs, CCTV, clear desk/screen.
A3: CZ Act 110/2019 (personal data processing) | B3: Yes – direct | C3: Czech implementing act for GDPR. | D3: Same as GDPR.
A4: CZ Labour Code 262/2006 (H&S §101–108; monitoring §316) | B4: Yes – direct | C4: Applies to employees working in Czechia. | D4: Risk assessment, training, injury book, employee monitoring limits.
A5: CZ Act 309/2006 (additional H&S requirements) | B5: Yes – direct | C5: Competent person (OZO), electrical safety. | D5: OZO, inspections.
A6: CZ Gov. Decree 361/2007 (workplace hygiene) | B6: Yes – direct | C6: Minimum conditions for workplaces and screen work. | D6: Lighting, temperature, ergonomics.
A7: CZ Act 133/1985 + Decree 246/2001 (fire protection) | B7: Yes – direct | C7: Every company with premises. | D7: Extinguishers, escape routes, fire training.
A8: CZ Act 171/2023 (whistleblower protection) | B8: Conditional | C8: Internal channel mandatory from 50 employees. | D8: Channel, designated person. | E8: Confirm Czech entity headcount.
A9: CZ Act 435/2004 (employment – disability quota) | B9: Conditional | C9: Quota from 25 employees. | D9: HR/payroll. | E9: Confirm Czech entity headcount.
A10: CZ Act 542/2020 (end-of-life products / WEEE) | B10: Yes – direct | C10: Disposal of electronic equipment. | D10: IT disposal.
A11: ISO/IEC 27001:2022 | B11: Voluntary – target | C11: Certification expected by enterprise customers. | D11: Annex A.7 physical controls + people controls.
A12: SOC 2 (AICPA TSC) | B12: Voluntary – target | C12: Expected by US customers (US expansion). | D12: CC6.4 physical access, CC6.5 disposal, CC7 incidents.
A13: NIS2 / CZ Act 264/2025 (Cybersecurity Act) | B13: Indirect – customer flow-down | C13: Duvo supplies banks and critical entities, which must secure their supply chain (Art 21(2)(d)). Direct applicability depends on size/sector test – to verify. | D13: Physical/environmental security, HR security, access control, hygiene and training. | E13: CZ Act in force since 1 Nov 2025.
A14: DORA (EU 2022/2554) | B14: Indirect – contractual | C14: Not a financial entity, but bank customers must include DORA contract terms with ICT providers, including audit and access/inspection rights. | D14: Client-visit mode = on-site inspection readiness.
A15: EU AI Act – Art 4 (AI literacy) | B15: Yes – direct | C15: Duvo provides and deploys AI systems; staff AI literacy obligation applies. | D15: Training content (PL-05), meeting AI note-takers.
A16: ISO/IEC 42001 | B16: Optional | C16: AI management system; differentiator for an AI provider. | D16: Light touch for the office.
A17: UK GDPR / DPA 2018 | B17: Indirect | C17: UK retail customers' data handled by Duvo staff. | D17: Handling of customer data on site.
A18: PCI DSS | B18: Not applicable | C18: No cardholder data handled (to confirm). | D18: Used only as yardstick for ☠☠☠ Hard physical controls.
A19: Cyber Resilience Act, Data Act, European Accessibility Act | B19: Out of scope here | C19: Product-level obligations, not office. | D19: None. | E19: Assess separately for the product.
A20: CZ Act 266/2025 (critical infrastructure) | B20: Not applicable | C20: Duvo is not designated critical infrastructure. | D20: None.
